gce/__init__.py
gce/gce.py
gce-1.0.2.dist-info/LICENSE
gce-1.0.2.dist-info/METADATA
gce-1.0.2.dist-info/WHEEL
gce-1.0.2.dist-info/entry_points.txt
gce-1.0.2.dist-info/top_level.txt
gce-1.0.2.dist-info/RECORD
