Metadata-Version: 2.1
Name: gce
Version: 1.0.2
Summary: Script Python pour interroger un module Teleinfo de GCE Electronics
Home-page: https://github.com/rene-d/gce
Author: Rene Devichi
Author-email: rene.github@gmail.com
License: UNKNOWN
Project-URL: Source, https://github.com/rene-d/gce
Project-URL: Bug Reports, https://github.com/rene-d/gce/issues
Keywords: teleinfo teleinformation gce
Platform: UNKNOWN
Classifier: License :: Public Domain
Classifier: Operating System :: OS Independent
Classifier: Topic :: Home Automation
Classifier: Programming Language :: Python :: 3
Classifier: Programming Language :: Python :: 3.5
Classifier: Programming Language :: Python :: 3.6
Classifier: Programming Language :: Python :: 3.7
Classifier: Programming Language :: Python :: 3.8
Requires-Python: >=3.5, <4
Requires-Dist: requests
